troncli/__init__.py
troncli/cli.py
troncli/constants.py
troncli/h_config.py
troncli/h_imode.py
troncli/h_init.py
troncli/h_log.py
troncli/h_status.py
troncli/h_worker.py
troncli/json_store.py
troncli/utils.py
troncli/xml_store.py
troncli-1.0.6.data/scripts/tron-cli
troncli-1.0.6.dist-info/LICENSE
troncli-1.0.6.dist-info/METADATA
troncli-1.0.6.dist-info/WHEEL
troncli-1.0.6.dist-info/top_level.txt
troncli-1.0.6.dist-info/RECORD
