Metadata-Version: 2.1
Name: troncli
Version: 1.0.6
Summary: A command line tool to monitor and manage tron nodes.
Home-page: https://github.com/tronprotocol/tron-cli
Author: Weiyu X
Author-email: weiyu@tron.network
License: UNKNOWN
Platform: UNKNOWN
Classifier: Environment :: Console
Classifier: License :: OSI Approved :: MIT License
Classifier: Operating System :: OS Independent
Classifier: Programming Language :: Python :: 3
Classifier: Programming Language :: Python :: 3.6
Classifier: Programming Language :: Python :: 3.7
Requires-Dist: bleach
Requires-Dist: cbox
Requires-Dist: certifi
Requires-Dist: chardet
Requires-Dist: colorama
Requires-Dist: docutils
Requires-Dist: idna
Requires-Dist: pkginfo
Requires-Dist: psutil
Requires-Dist: Pygments
Requires-Dist: readme-renderer
Requires-Dist: requests
Requires-Dist: requests-toolbelt
Requires-Dist: six
Requires-Dist: tqdm
Requires-Dist: urllib3
Requires-Dist: webencodings
Requires-Dist: lxml
